stove/__init__.py
stove/__main__.py
stove/hello.py
stove-0.0.7.dist-info/METADATA
stove-0.0.7.dist-info/WHEEL
stove-0.0.7.dist-info/entry_points.txt
stove-0.0.7.dist-info/RECORD
