Metadata-Version: 2.1
Name: stove
Version: 0.0.7
Summary: A warm place to cook your apps with.
Author: Marco Di Sarno
Author-email: disarno@k3b.de
Requires-Python: >=3.12,<4.0
Classifier: Programming Language :: Python :: 3
Classifier: Programming Language :: Python :: 3.12
